<internal size="1003">
  <page size="60">
    <parms>
      <parm type="opt" name="1" value="hello/index" />
      <parm type="lvl" name="color" value="pink" />
    </parms>
  </page>
  <page size="62">
    <parms>
      <parm type="opt" name="1" value="hello/index" />
      <parm type="prm" name="reset" value="1" />
      <parm type="lvl" name="color" value="orange" />
    </parms>
  </page>
  <page size="61">
    <parms>
      <parm type="opt" name="1" value="hello/index" />
      <parm type="prm" name="clean" value="1" />
      <parm type="lvl" name="color" value="brown" />
    </parms>
  </page>
  <page size="62">
    <parms>
      <parm type="opt" name="1" value="hello/index" />
      <parm type="prm" name="sandbox" value="1" />
      <parm type="lvl" name="color" value="purple" />
    </parms>
  </page>
  <page size="61">
    <parms>
      <parm type="opt" name="1" value="hello/index" />
      <parm type="prm" name="function" value="1" />
      <parm type="lvl" name="color" value="green" />
    </parms>
  </page>
  <page size="60">
    <parms>
      <parm type="opt" name="1" value="hello/index" />
      <parm type="prm" name="reset" value="1" />
      <parm type="prm" name="function" value="1" />
      <parm type="lvl" name="color" value="blue" />
    </parms>
  </page>
  <page size="62">
    <parms>
      <parm type="opt" name="1" value="hello/index" />
      <parm type="prm" name="clean" value="1" />
      <parm type="prm" name="function" value="1" />
      <parm type="lvl" name="color" value="yellow" />
    </parms>
  </page>
  <page size="59">
    <parms>
      <parm type="opt" name="1" value="hello/index" />
      <parm type="prm" name="sandbox" value="1" />
      <parm type="prm" name="function" value="1" />
      <parm type="lvl" name="color" value="red" />
    </parms>
  </page>
  <code size="63" parm="$color='pink'" />
  <code size="63">
    <parms>
      <parm type="prm" name="reset" value="1" />
      <parm type="lvl" name="color" value="orange" />
    </parms>
  </code>
  <code size="63">
    <parms>
      <parm type="prm" name="clean" value="1" />
      <parm type="lvl" name="color" value="brown" />
    </parms>
  </code>
  <code size="63">
    <parms>
      <parm type="prm" name="sandbox" value="1" />
      <parm type="lvl" name="color" value="purple" />
    </parms>
  </code>
  <code size="53">
    <parms>
      <parm type="prm" name="function" value="1" />
      <parm type="lvl" name="color" value="green" />
    </parms>
  </code>
  <code size="53">
    <parms>
      <parm type="prm" name="reset" value="1" />
      <parm type="prm" name="function" value="1" />
      <parm type="lvl" name="color" value="blue" />
    </parms>
  </code>
  <code size="53">
    <parms>
      <parm type="prm" name="clean" value="1" />
      <parm type="prm" name="function" value="1" />
      <parm type="lvl" name="color" value="yellow" />
    </parms>
  </code>
  <code size="53">
    <parms>
      <parm type="prm" name="sandbox" value="1" />
      <parm type="prm" name="function" value="1" />
      <parm type="lvl" name="color" value="red" />
    </parms>
  </code>
</internal>